{
  "labels": [
    "05/26 14:21",
    "06/01 03:29",
    "06/06 12:01",
    "06/11 21:01",
    "06/18 00:01",
    "06/23 12:01",
    "06/30 12:01",
    "07/06 12:01"
  ],
  "datasets": [
    {
      "label": "Copilot Total",
      "type": "bar",
      "data": [
        8729,
        10891,
        13080,
        15561,
        17218,
        17890,
        21033,
        27156
      ],
      "backgroundColor": "#93c5fd",
      "borderColor": "#93c5fd",
      "borderWidth": 1,
      "yAxisID": "y",
      "order": 2
    },
    {
      "label": "Copilot Merged",
      "type": "bar",
      "data": [
        1594,
        3171,
        4678,
        6607,
        8982,
        10453,
        12513,
        15656
      ],
      "backgroundColor": "#2563eb",
      "borderColor": "#2563eb",
      "borderWidth": 1,
      "yAxisID": "y",
      "order": 2
    },
    {
      "label": "Copilot Success % (Ready)",
      "type": "line",
      "data": [
        75.94092424964268,
        83.14105925537494,
        84.39473209453364,
        87.60275788915408,
        91.42915309446255,
        92.06447067112911,
        92.55862119979288,
        92.11579195104731
      ],
      "borderColor": "#1d4ed8",
      "backgroundColor": "rgba(255, 255, 255, 0.8)",
      "borderWidth": 3,
      "pointRadius": 3,
      "pointHoverRadius": 5,
      "fill": false,
      "yAxisID": "y1",
      "order": 1,
      "rateType": "ready"
    },
    {
      "label": "Copilot Success % (All)",
      "type": "line",
      "data": [
        18.260969183182496,
        29.115783674593704,
        35.764525993883794,
        42.45871087976351,
        52.166337553722855,
        58.429290106204576,
        59.49222650121237,
        57.652084253940195
      ],
      "borderColor": "#1d4ed8",
      "backgroundColor": "rgba(255, 255, 255, 0.8)",
      "borderWidth": 3,
      "pointRadius": 3,
      "pointHoverRadius": 5,
      "fill": false,
      "yAxisID": "y1",
      "order": 1,
      "hidden": true,
      "rateType": "total"
    },
    {
      "label": "Codex Total",
      "type": "bar",
      "data": [
        54211,
        73489,
        157281,
        266480,
        369603,
        454235,
        547930,
        615390
      ],
      "backgroundColor": "#fca5a5",
      "borderColor": "#fca5a5",
      "borderWidth": 1,
      "yAxisID": "y",
      "order": 2
    },
    {
      "label": "Codex Merged",
      "type": "bar",
      "data": [
        44230,
        61021,
        129172,
        223695,
        314239,
        389610,
        473167,
        532684
      ],
      "backgroundColor": "#dc2626",
      "borderColor": "#dc2626",
      "borderWidth": 1,
      "yAxisID": "y",
      "order": 2
    },
    {
      "label": "Codex Success % (Ready)",
      "type": "line",
      "data": [
        85.80352293008458,
        86.05658035764652,
        85.78012418235548,
        87.07439830907626,
        87.42679401609766,
        87.54789056794561,
        87.37724413781896,
        87.55820815053823
      ],
      "borderColor": "#b91c1c",
      "backgroundColor": "rgba(255, 255, 255, 0.8)",
      "borderWidth": 3,
      "pointRadius": 3,
      "pointHoverRadius": 5,
      "fill": false,
      "yAxisID": "y1",
      "order": 1,
      "rateType": "ready"
    },
    {
      "label": "Codex Success % (All)",
      "type": "line",
      "data": [
        81.58860747818709,
        83.0341955938984,
        82.12816551268112,
        83.94438607024918,
        85.02068435591703,
        85.77278281065968,
        86.35537386162466,
        86.56039259656478
      ],
      "borderColor": "#b91c1c",
      "backgroundColor": "rgba(255, 255, 255, 0.8)",
      "borderWidth": 3,
      "pointRadius": 3,
      "pointHoverRadius": 5,
      "fill": false,
      "yAxisID": "y1",
      "order": 1,
      "hidden": true,
      "rateType": "total"
    },
    {
      "label": "Cursor Total",
      "type": "bar",
      "data": [
        null,
        null,
        423,
        964,
        1364,
        2077,
        3120,
        9027
      ],
      "backgroundColor": "#c4b5fd",
      "borderColor": "#c4b5fd",
      "borderWidth": 1,
      "yAxisID": "y",
      "order": 2
    },
    {
      "label": "Cursor Merged",
      "type": "bar",
      "data": [
        null,
        null,
        318,
        720,
        1014,
        1534,
        2307,
        6722
      ],
      "backgroundColor": "#7c3aed",
      "borderColor": "#7c3aed",
      "borderWidth": 1,
      "yAxisID": "y",
      "order": 2
    },
    {
      "label": "Cursor Success % (Ready)",
      "type": "line",
      "data": [
        null,
        null,
        80.71065989847716,
        78.94736842105263,
        77.11026615969581,
        76.12903225806451,
        76.26446280991736,
        75.53657714349927
      ],
      "borderColor": "#6d28d9",
      "backgroundColor": "rgba(255, 255, 255, 0.8)",
      "borderWidth": 3,
      "pointRadius": 3,
      "pointHoverRadius": 5,
      "fill": false,
      "yAxisID": "y1",
      "order": 1,
      "rateType": "ready"
    },
    {
      "label": "Cursor Success % (All)",
      "type": "line",
      "data": [
        null,
        null,
        75.177304964539,
        74.68879668049793,
        74.34017595307918,
        73.85652383245065,
        73.9423076923077,
        74.46549241165393
      ],
      "borderColor": "#6d28d9",
      "backgroundColor": "rgba(255, 255, 255, 0.8)",
      "borderWidth": 3,
      "pointRadius": 3,
      "pointHoverRadius": 5,
      "fill": false,
      "yAxisID": "y1",
      "order": 1,
      "hidden": true,
      "rateType": "total"
    },
    {
      "label": "Devin Total",
      "type": "bar",
      "data": [
        null,
        null,
        27641,
        28226,
        29111,
        29864,
        29410,
        30157
      ],
      "backgroundColor": "#86efac",
      "borderColor": "#86efac",
      "borderWidth": 1,
      "yAxisID": "y",
      "order": 2
    },
    {
      "label": "Devin Merged",
      "type": "bar",
      "data": [
        null,
        null,
        16799,
        17186,
        17778,
        18217,
        18771,
        19298
      ],
      "backgroundColor": "#059669",
      "borderColor": "#059669",
      "borderWidth": 1,
      "yAxisID": "y",
      "order": 2
    },
    {
      "label": "Devin Success % (Ready)",
      "type": "line",
      "data": [
        null,
        null,
        66.77664268394483,
        66.55307284204004,
        66.30860467718473,
        65.79384570933257,
        65.74781085814361,
        65.95126619049246
      ],
      "borderColor": "#047857",
      "backgroundColor": "rgba(255, 255, 255, 0.8)",
      "borderWidth": 3,
      "pointRadius": 3,
      "pointHoverRadius": 5,
      "fill": false,
      "yAxisID": "y1",
      "order": 1,
      "rateType": "ready"
    },
    {
      "label": "Devin Success % (All)",
      "type": "line",
      "data": [
        null,
        null,
        60.77565934662277,
        60.887125345426206,
        61.069698739308166,
        60.999866059469596,
        63.82522951377083,
        63.991776370328616
      ],
      "borderColor": "#047857",
      "backgroundColor": "rgba(255, 255, 255, 0.8)",
      "borderWidth": 3,
      "pointRadius": 3,
      "pointHoverRadius": 5,
      "fill": false,
      "yAxisID": "y1",
      "order": 1,
      "hidden": true,
      "rateType": "total"
    },
    {
      "label": "Codegen Total",
      "type": "bar",
      "data": [
        null,
        null,
        null,
        3991,
        3946,
        4124,
        4221,
        4161
      ],
      "backgroundColor": "#fed7aa",
      "borderColor": "#fed7aa",
      "borderWidth": 1,
      "yAxisID": "y",
      "order": 2
    },
    {
      "label": "Codegen Merged",
      "type": "bar",
      "data": [
        null,
        null,
        null,
        1466,
        1551,
        1675,
        1724,
        1689
      ],
      "backgroundColor": "#d97706",
      "borderColor": "#d97706",
      "borderWidth": 1,
      "yAxisID": "y",
      "order": 2
    },
    {
      "label": "Codegen Success % (Ready)",
      "type": "line",
      "data": [
        null,
        null,
        null,
        87.00296735905044,
        84.56924754634679,
        82.55298176441596,
        80.90098545283905,
        79.82041587901702
      ],
      "borderColor": "#b45309",
      "backgroundColor": "rgba(255, 255, 255, 0.8)",
      "borderWidth": 3,
      "pointRadius": 3,
      "pointHoverRadius": 5,
      "fill": false,
      "yAxisID": "y1",
      "order": 1,
      "rateType": "ready"
    },
    {
      "label": "Codegen Success % (All)",
      "type": "line",
      "data": [
        null,
        null,
        null,
        36.73264845903282,
        39.30562595032945,
        40.61590688651794,
        40.843402037431886,
        40.59120403749098
      ],
      "borderColor": "#b45309",
      "backgroundColor": "rgba(255, 255, 255, 0.8)",
      "borderWidth": 3,
      "pointRadius": 3,
      "pointHoverRadius": 5,
      "fill": false,
      "yAxisID": "y1",
      "order": 1,
      "hidden": true,
      "rateType": "total"
    }
  ]
}