{
  "labels": [
    "05/26 14:21",
    "05/30 18:01",
    "06/04 06:01",
    "06/08 06:01",
    "06/12 12:01",
    "06/17 06:01",
    "06/22 00:02",
    "06/25 15:01"
  ],
  "datasets": [
    {
      "label": "Copilot Total",
      "type": "bar",
      "data": [
        8729,
        10286,
        12135,
        13808,
        15794,
        17011,
        17581,
        18062
      ],
      "backgroundColor": "#93c5fd",
      "borderColor": "#93c5fd",
      "borderWidth": 1,
      "yAxisID": "y",
      "order": 2
    },
    {
      "label": "Copilot Merged",
      "type": "bar",
      "data": [
        1594,
        2733,
        4141,
        5198,
        6824,
        8835,
        10197,
        10981
      ],
      "backgroundColor": "#2563eb",
      "borderColor": "#2563eb",
      "borderWidth": 1,
      "yAxisID": "y",
      "order": 2
    },
    {
      "label": "Copilot Success %",
      "type": "line",
      "data": [
        18.260969183182496,
        26.570095275131244,
        34.124433456942725,
        37.64484356894554,
        43.2062808661517,
        51.93698195285403,
        58.00011375917183,
        60.79614660613443
      ],
      "borderColor": "#1d4ed8",
      "backgroundColor": "rgba(255, 255, 255, 0.8)",
      "borderWidth": 3,
      "pointRadius": 3,
      "pointHoverRadius": 5,
      "fill": false,
      "yAxisID": "y1",
      "order": 1
    },
    {
      "label": "Codex Total",
      "type": "bar",
      "data": [
        54211,
        72215,
        95829,
        193372,
        277604,
        357049,
        435356,
        487665
      ],
      "backgroundColor": "#fca5a5",
      "borderColor": "#fca5a5",
      "borderWidth": 1,
      "yAxisID": "y",
      "order": 2
    },
    {
      "label": "Codex Merged",
      "type": "bar",
      "data": [
        44230,
        60080,
        79045,
        160278,
        233461,
        303053,
        373069,
        419239
      ],
      "backgroundColor": "#dc2626",
      "borderColor": "#dc2626",
      "borderWidth": 1,
      "yAxisID": "y",
      "order": 2
    },
    {
      "label": "Codex Success %",
      "type": "line",
      "data": [
        81.58860747818709,
        83.1960119088832,
        82.48546890815932,
        82.8858366257783,
        84.09857206668492,
        84.87714571389361,
        85.69285825852864,
        85.96864650938657
      ],
      "borderColor": "#b91c1c",
      "backgroundColor": "rgba(255, 255, 255, 0.8)",
      "borderWidth": 3,
      "pointRadius": 3,
      "pointHoverRadius": 5,
      "fill": false,
      "yAxisID": "y1",
      "order": 1
    },
    {
      "label": "Cursor Total",
      "type": "bar",
      "data": [
        null,
        null,
        null,
        644,
        1008,
        1298,
        1863,
        2452
      ],
      "backgroundColor": "#c4b5fd",
      "borderColor": "#c4b5fd",
      "borderWidth": 1,
      "yAxisID": "y",
      "order": 2
    },
    {
      "label": "Cursor Merged",
      "type": "bar",
      "data": [
        null,
        null,
        null,
        488,
        753,
        975,
        1379,
        1803
      ],
      "backgroundColor": "#7c3aed",
      "borderColor": "#7c3aed",
      "borderWidth": 1,
      "yAxisID": "y",
      "order": 2
    },
    {
      "label": "Cursor Success %",
      "type": "line",
      "data": [
        null,
        null,
        null,
        75.77639751552795,
        74.70238095238095,
        75.115562403698,
        74.020397208803,
        73.53181076672104
      ],
      "borderColor": "#6d28d9",
      "backgroundColor": "rgba(255, 255, 255, 0.8)",
      "borderWidth": 3,
      "pointRadius": 3,
      "pointHoverRadius": 5,
      "fill": false,
      "yAxisID": "y1",
      "order": 1
    },
    {
      "label": "Devin Total",
      "type": "bar",
      "data": [
        null,
        null,
        27425,
        27810,
        28350,
        28987,
        29757,
        28980
      ],
      "backgroundColor": "#86efac",
      "borderColor": "#86efac",
      "borderWidth": 1,
      "yAxisID": "y",
      "order": 2
    },
    {
      "label": "Devin Merged",
      "type": "bar",
      "data": [
        null,
        null,
        16696,
        16908,
        17293,
        17726,
        18174,
        18476
      ],
      "backgroundColor": "#059669",
      "borderColor": "#059669",
      "borderWidth": 1,
      "yAxisID": "y",
      "order": 2
    },
    {
      "label": "Devin Success %",
      "type": "line",
      "data": [
        null,
        null,
        60.87876025524157,
        60.79827400215749,
        60.998236331569665,
        61.1515506951392,
        61.07470511140236,
        63.75431331953071
      ],
      "borderColor": "#047857",
      "backgroundColor": "rgba(255, 255, 255, 0.8)",
      "borderWidth": 3,
      "pointRadius": 3,
      "pointHoverRadius": 5,
      "fill": false,
      "yAxisID": "y1",
      "order": 1
    },
    {
      "label": "Codegen Total",
      "type": "bar",
      "data": [
        null,
        null,
        null,
        null,
        4075,
        3927,
        4048,
        4150
      ],
      "backgroundColor": "#fed7aa",
      "borderColor": "#fed7aa",
      "borderWidth": 1,
      "yAxisID": "y",
      "order": 2
    },
    {
      "label": "Codegen Merged",
      "type": "bar",
      "data": [
        null,
        null,
        null,
        null,
        1730,
        1559,
        1616,
        1692
      ],
      "backgroundColor": "#d97706",
      "borderColor": "#d97706",
      "borderWidth": 1,
      "yAxisID": "y",
      "order": 2
    },
    {
      "label": "Codegen Success %",
      "type": "line",
      "data": [
        null,
        null,
        null,
        null,
        42.45398773006135,
        39.6995161701044,
        39.920948616600796,
        40.7710843373494
      ],
      "borderColor": "#b45309",
      "backgroundColor": "rgba(255, 255, 255, 0.8)",
      "borderWidth": 3,
      "pointRadius": 3,
      "pointHoverRadius": 5,
      "fill": false,
      "yAxisID": "y1",
      "order": 1
    }
  ]
}