{
  "labels": [
    "05/26 14:21",
    "06/05 19:34",
    "06/15 18:01",
    "06/26 18:14",
    "07/08 03:24",
    "07/19 03:26",
    "07/30 00:02",
    "08/10 03:30"
  ],
  "datasets": [
    {
      "label": "Copilot Total",
      "type": "bar",
      "data": [
        8729,
        12869,
        16150,
        18744,
        28875,
        44438,
        62275,
        84214
      ],
      "backgroundColor": "#93c5fd",
      "borderColor": "#93c5fd",
      "borderWidth": 1,
      "yAxisID": "y",
      "order": 2
    },
    {
      "label": "Copilot Merged",
      "type": "bar",
      "data": [
        1594,
        4567,
        8196,
        11336,
        16558,
        24856,
        36438,
        50648
      ],
      "backgroundColor": "#2563eb",
      "borderColor": "#2563eb",
      "borderWidth": 1,
      "yAxisID": "y",
      "order": 2
    },
    {
      "label": "Copilot Success % (Ready)",
      "type": "line",
      "data": [
        75.94092424964268,
        85.86200413611581,
        90.64366290643663,
        92.2976713890246,
        92.0963346126036,
        91.61475802587447,
        92.15244935636429,
        92.22141296431172
      ],
      "borderColor": "#1d4ed8",
      "backgroundColor": "rgba(255, 255, 255, 0.8)",
      "borderWidth": 3,
      "pointRadius": 3,
      "pointHoverRadius": 5,
      "fill": false,
      "yAxisID": "y1",
      "order": 1,
      "rateType": "ready"
    },
    {
      "label": "Copilot Success % (All)",
      "type": "line",
      "data": [
        18.260969183182496,
        35.48838293573704,
        50.74922600619195,
        60.47801963294921,
        57.34372294372294,
        55.93411044601467,
        58.5114411882778,
        60.1420191417104
      ],
      "borderColor": "#1d4ed8",
      "backgroundColor": "rgba(255, 255, 255, 0.8)",
      "borderWidth": 3,
      "pointRadius": 3,
      "pointHoverRadius": 5,
      "fill": false,
      "yAxisID": "y1",
      "order": 1,
      "hidden": true,
      "rateType": "total"
    },
    {
      "label": "Codex Total",
      "type": "bar",
      "data": [
        54211,
        142096,
        331624,
        502355,
        636707,
        746663,
        853794,
        979878
      ],
      "backgroundColor": "#fca5a5",
      "borderColor": "#fca5a5",
      "borderWidth": 1,
      "yAxisID": "y",
      "order": 2
    },
    {
      "label": "Codex Merged",
      "type": "bar",
      "data": [
        44230,
        116376,
        280913,
        432522,
        551780,
        650396,
        746392,
        858301
      ],
      "backgroundColor": "#dc2626",
      "borderColor": "#dc2626",
      "borderWidth": 1,
      "yAxisID": "y",
      "order": 2
    },
    {
      "label": "Codex Success % (Ready)",
      "type": "line",
      "data": [
        85.80352293008458,
        85.10750329091707,
        87.4091798728596,
        87.15018285495522,
        87.64882016091242,
        88.0488874689309,
        88.31191572889465,
        88.44707196530958
      ],
      "borderColor": "#b91c1c",
      "backgroundColor": "rgba(255, 255, 255, 0.8)",
      "borderWidth": 3,
      "pointRadius": 3,
      "pointHoverRadius": 5,
      "fill": false,
      "yAxisID": "y1",
      "order": 1,
      "rateType": "ready"
    },
    {
      "label": "Codex Success % (All)",
      "type": "line",
      "data": [
        81.58860747818709,
        81.89956086026349,
        84.70828408076618,
        86.09887430203742,
        86.66152563109877,
        87.10703490061782,
        87.42061902519812,
        87.59263908364102
      ],
      "borderColor": "#b91c1c",
      "backgroundColor": "rgba(255, 255, 255, 0.8)",
      "borderWidth": 3,
      "pointRadius": 3,
      "pointHoverRadius": 5,
      "fill": false,
      "yAxisID": "y1",
      "order": 1,
      "hidden": true,
      "rateType": "total"
    },
    {
      "label": "Cursor Total",
      "type": "bar",
      "data": [
        null,
        343,
        1206,
        2659,
        10649,
        22119,
        42018,
        71459
      ],
      "backgroundColor": "#c4b5fd",
      "borderColor": "#c4b5fd",
      "borderWidth": 1,
      "yAxisID": "y",
      "order": 2
    },
    {
      "label": "Cursor Merged",
      "type": "bar",
      "data": [
        null,
        254,
        910,
        1950,
        8012,
        16749,
        28146,
        42619
      ],
      "backgroundColor": "#7c3aed",
      "borderColor": "#7c3aed",
      "borderWidth": 1,
      "yAxisID": "y",
      "order": 2
    },
    {
      "label": "Cursor Success % (Ready)",
      "type": "line",
      "data": [
        null,
        80.12618296529969,
        79.40663176265271,
        75.78701904391761,
        76.23215984776404,
        76.33305988515177,
        74.67367080547596,
        79.52938102968893
      ],
      "borderColor": "#6d28d9",
      "backgroundColor": "rgba(255, 255, 255, 0.8)",
      "borderWidth": 3,
      "pointRadius": 3,
      "pointHoverRadius": 5,
      "fill": false,
      "yAxisID": "y1",
      "order": 1,
      "rateType": "ready"
    },
    {
      "label": "Cursor Success % (All)",
      "type": "line",
      "data": [
        null,
        74.05247813411079,
        75.45605306799337,
        73.33584054155698,
        75.23711146586534,
        75.7222297572223,
        66.9855776095959,
        59.64119285184511
      ],
      "borderColor": "#6d28d9",
      "backgroundColor": "rgba(255, 255, 255, 0.8)",
      "borderWidth": 3,
      "pointRadius": 3,
      "pointHoverRadius": 5,
      "fill": false,
      "yAxisID": "y1",
      "order": 1,
      "hidden": true,
      "rateType": "total"
    },
    {
      "label": "Devin Total",
      "type": "bar",
      "data": [
        null,
        27679,
        28683,
        29122,
        30372,
        31492,
        33160,
        35605
      ],
      "backgroundColor": "#86efac",
      "borderColor": "#86efac",
      "borderWidth": 1,
      "yAxisID": "y",
      "order": 2
    },
    {
      "label": "Devin Merged",
      "type": "bar",
      "data": [
        null,
        16869,
        17500,
        18578,
        19421,
        20022,
        20954,
        22477
      ],
      "backgroundColor": "#059669",
      "borderColor": "#059669",
      "borderWidth": 1,
      "yAxisID": "y",
      "order": 2
    },
    {
      "label": "Devin Success % (Ready)",
      "type": "line",
      "data": [
        null,
        67.28759473474271,
        66.24271330153682,
        65.71398252626366,
        65.92104816537116,
        65.61148250098309,
        65.20616150614595,
        65.12618433633703
      ],
      "borderColor": "#047857",
      "backgroundColor": "rgba(255, 255, 255, 0.8)",
      "borderWidth": 3,
      "pointRadius": 3,
      "pointHoverRadius": 5,
      "fill": false,
      "yAxisID": "y1",
      "order": 1,
      "rateType": "ready"
    },
    {
      "label": "Devin Success % (All)",
      "type": "line",
      "data": [
        null,
        60.945120849741684,
        61.01174911968762,
        63.793695487947254,
        63.94376399315159,
        63.57805156865236,
        63.190591073582624,
        63.128774048588674
      ],
      "borderColor": "#047857",
      "backgroundColor": "rgba(255, 255, 255, 0.8)",
      "borderWidth": 3,
      "pointRadius": 3,
      "pointHoverRadius": 5,
      "fill": false,
      "yAxisID": "y1",
      "order": 1,
      "hidden": true,
      "rateType": "total"
    },
    {
      "label": "Codegen Total",
      "type": "bar",
      "data": [
        null,
        null,
        4169,
        4163,
        4232,
        4546,
        4917,
        5239
      ],
      "backgroundColor": "#fed7aa",
      "borderColor": "#fed7aa",
      "borderWidth": 1,
      "yAxisID": "y",
      "order": 2
    },
    {
      "label": "Codegen Merged",
      "type": "bar",
      "data": [
        null,
        null,
        1522,
        1694,
        1725,
        1902,
        2130,
        2288
      ],
      "backgroundColor": "#d97706",
      "borderColor": "#d97706",
      "borderWidth": 1,
      "yAxisID": "y",
      "order": 2
    },
    {
      "label": "Codegen Success % (Ready)",
      "type": "line",
      "data": [
        null,
        null,
        85.50561797752809,
        81.48148148148148,
        79.09215955983494,
        76.91063485644966,
        75.42492917847025,
        72.51980982567353
      ],
      "borderColor": "#b45309",
      "backgroundColor": "rgba(255, 255, 255, 0.8)",
      "borderWidth": 3,
      "pointRadius": 3,
      "pointHoverRadius": 5,
      "fill": false,
      "yAxisID": "y1",
      "order": 1,
      "rateType": "ready"
    },
    {
      "label": "Codegen Success % (All)",
      "type": "line",
      "data": [
        null,
        null,
        36.50755576876949,
        40.691808791736726,
        40.76086956521739,
        41.8389793224813,
        43.319097010372175,
        43.67245657568238
      ],
      "borderColor": "#b45309",
      "backgroundColor": "rgba(255, 255, 255, 0.8)",
      "borderWidth": 3,
      "pointRadius": 3,
      "pointHoverRadius": 5,
      "fill": false,
      "yAxisID": "y1",
      "order": 1,
      "hidden": true,
      "rateType": "total"
    }
  ]
}