{
  "labels": [
    "05/26 14:21",
    "06/11 06:01",
    "06/29 06:01",
    "07/16 15:01",
    "08/03 03:33",
    "08/21 13:23",
    "09/08 06:03",
    "09/28 18:03"
  ],
  "datasets": [
    {
      "label": "Copilot Total",
      "type": "bar",
      "data": [
        8729,
        15172,
        20217,
        40159,
        70189,
        111648,
        164188,
        239231
      ],
      "backgroundColor": "#93c5fd",
      "borderColor": "#93c5fd",
      "borderWidth": 1,
      "yAxisID": "y",
      "order": 2
    },
    {
      "label": "Copilot Merged",
      "type": "bar",
      "data": [
        1594,
        6365,
        12123,
        22432,
        41259,
        68089,
        100820,
        146981
      ],
      "backgroundColor": "#2563eb",
      "borderColor": "#2563eb",
      "borderWidth": 1,
      "yAxisID": "y",
      "order": 2
    },
    {
      "label": "Copilot Success % (Ready)",
      "type": "line",
      "data": [
        75.94092424964268,
        87.29941023179262,
        92.45729103111654,
        91.6227586488584,
        92.25454464145966,
        92.43812704489608,
        92.63393882595074,
        92.77580700137604
      ],
      "borderColor": "#1d4ed8",
      "backgroundColor": "rgba(255, 255, 255, 0.8)",
      "borderWidth": 3,
      "pointRadius": 3,
      "pointHoverRadius": 5,
      "fill": false,
      "yAxisID": "y1",
      "order": 1,
      "rateType": "ready"
    },
    {
      "label": "Copilot Success % (All)",
      "type": "line",
      "data": [
        18.260969183182496,
        41.95228051674136,
        59.964386407478855,
        55.85796459075176,
        58.78271524027981,
        60.985418458010884,
        61.40521840816625,
        61.43894394957176
      ],
      "borderColor": "#1d4ed8",
      "backgroundColor": "rgba(255, 255, 255, 0.8)",
      "borderWidth": 3,
      "pointRadius": 3,
      "pointHoverRadius": 5,
      "fill": false,
      "yAxisID": "y1",
      "order": 1,
      "hidden": true,
      "rateType": "total"
    },
    {
      "label": "Codex Total",
      "type": "bar",
      "data": [
        54211,
        253021,
        533003,
        722678,
        891002,
        1156623,
        1415130,
        1709980
      ],
      "backgroundColor": "#fca5a5",
      "borderColor": "#fca5a5",
      "borderWidth": 1,
      "yAxisID": "y",
      "order": 2
    },
    {
      "label": "Codex Merged",
      "type": "bar",
      "data": [
        44230,
        211954,
        460076,
        629059,
        779500,
        1010581,
        1235527,
        1486787
      ],
      "backgroundColor": "#dc2626",
      "borderColor": "#dc2626",
      "borderWidth": 1,
      "yAxisID": "y",
      "order": 2
    },
    {
      "label": "Codex Success % (Ready)",
      "type": "line",
      "data": [
        85.80352293008458,
        86.9102047343538,
        87.34636224526604,
        87.98864787140596,
        88.36666213213621,
        88.18048631937712,
        88.06096208507836,
        87.6760627749115
      ],
      "borderColor": "#b91c1c",
      "backgroundColor": "rgba(255, 255, 255, 0.8)",
      "borderWidth": 3,
      "pointRadius": 3,
      "pointHoverRadius": 5,
      "fill": false,
      "yAxisID": "y1",
      "order": 1,
      "rateType": "ready"
    },
    {
      "label": "Codex Success % (All)",
      "type": "line",
      "data": [
        81.58860747818709,
        83.76933139937002,
        86.31771303351013,
        87.04554448869344,
        87.48577444270607,
        87.37341380899394,
        87.30837449562938,
        86.94762511842244
      ],
      "borderColor": "#b91c1c",
      "backgroundColor": "rgba(255, 255, 255, 0.8)",
      "borderWidth": 3,
      "pointRadius": 3,
      "pointHoverRadius": 5,
      "fill": false,
      "yAxisID": "y1",
      "order": 1,
      "hidden": true,
      "rateType": "total"
    },
    {
      "label": "Cursor Total",
      "type": "bar",
      "data": [
        null,
        921,
        2962,
        19415,
        52004,
        100661,
        133181,
        159449
      ],
      "backgroundColor": "#c4b5fd",
      "borderColor": "#c4b5fd",
      "borderWidth": 1,
      "yAxisID": "y",
      "order": 2
    },
    {
      "label": "Cursor Merged",
      "type": "bar",
      "data": [
        null,
        691,
        2177,
        14657,
        32676,
        56959,
        74667,
        90402
      ],
      "backgroundColor": "#7c3aed",
      "borderColor": "#7c3aed",
      "borderWidth": 1,
      "yAxisID": "y",
      "order": 2
    },
    {
      "label": "Cursor Success % (Ready)",
      "type": "line",
      "data": [
        null,
        80.16241299303944,
        75.88009759498084,
        76.17587443480069,
        76.67002979891598,
        82.63910047152703,
        88.04240166022073,
        92.89531012372066
      ],
      "borderColor": "#6d28d9",
      "backgroundColor": "rgba(255, 255, 255, 0.8)",
      "borderWidth": 3,
      "pointRadius": 3,
      "pointHoverRadius": 5,
      "fill": false,
      "yAxisID": "y1",
      "order": 1,
      "rateType": "ready"
    },
    {
      "label": "Cursor Success % (All)",
      "type": "line",
      "data": [
        null,
        75.0271444082519,
        73.49763673193787,
        75.49317537986093,
        62.83362818244751,
        56.58497332631307,
        56.06430346671072,
        56.6964985669399
      ],
      "borderColor": "#6d28d9",
      "backgroundColor": "rgba(255, 255, 255, 0.8)",
      "borderWidth": 3,
      "pointRadius": 3,
      "pointHoverRadius": 5,
      "fill": false,
      "yAxisID": "y1",
      "order": 1,
      "hidden": true,
      "rateType": "total"
    },
    {
      "label": "Devin Total",
      "type": "bar",
      "data": [
        null,
        28178,
        29337,
        31267,
        33905,
        37762,
        39791,
        42548
      ],
      "backgroundColor": "#86efac",
      "borderColor": "#86efac",
      "borderWidth": 1,
      "yAxisID": "y",
      "order": 2
    },
    {
      "label": "Devin Merged",
      "type": "bar",
      "data": [
        null,
        17152,
        18705,
        19933,
        21477,
        23857,
        24983,
        26262
      ],
      "backgroundColor": "#059669",
      "borderColor": "#059669",
      "borderWidth": 1,
      "yAxisID": "y",
      "order": 2
    },
    {
      "label": "Devin Success % (Ready)",
      "type": "line",
      "data": [
        null,
        66.65112302790082,
        65.68689422671724,
        65.7681140292992,
        65.34319094560058,
        65.17237611320549,
        64.84375,
        63.70406306852638
      ],
      "borderColor": "#047857",
      "backgroundColor": "rgba(255, 255, 255, 0.8)",
      "borderWidth": 3,
      "pointRadius": 3,
      "pointHoverRadius": 5,
      "fill": false,
      "yAxisID": "y1",
      "order": 1,
      "rateType": "ready"
    },
    {
      "label": "Devin Success % (All)",
      "type": "line",
      "data": [
        null,
        60.87018241181064,
        63.759075570099185,
        63.75091949979211,
        63.34463943371185,
        63.177268153169855,
        62.78555452237943,
        61.723230234088554
      ],
      "borderColor": "#047857",
      "backgroundColor": "rgba(255, 255, 255, 0.8)",
      "borderWidth": 3,
      "pointRadius": 3,
      "pointHoverRadius": 5,
      "fill": false,
      "yAxisID": "y1",
      "order": 1,
      "hidden": true,
      "rateType": "total"
    },
    {
      "label": "Codegen Total",
      "type": "bar",
      "data": [
        null,
        3935,
        4202,
        4466,
        5032,
        5682,
        6882,
        7760
      ],
      "backgroundColor": "#fed7aa",
      "borderColor": "#fed7aa",
      "borderWidth": 1,
      "yAxisID": "y",
      "order": 2
    },
    {
      "label": "Codegen Merged",
      "type": "bar",
      "data": [
        null,
        1434,
        1711,
        1847,
        2210,
        2498,
        2795,
        3004
      ],
      "backgroundColor": "#d97706",
      "borderColor": "#d97706",
      "borderWidth": 1,
      "yAxisID": "y",
      "order": 2
    },
    {
      "label": "Codegen Success % (Ready)",
      "type": "line",
      "data": [
        null,
        86.9090909090909,
        80.97491717936583,
        76.99041267194664,
        74.78849407783417,
        71.45308924485126,
        62.72441651705566,
        61.04450314976631
      ],
      "borderColor": "#b45309",
      "backgroundColor": "rgba(255, 255, 255, 0.8)",
      "borderWidth": 3,
      "pointRadius": 3,
      "pointHoverRadius": 5,
      "fill": false,
      "yAxisID": "y1",
      "order": 1,
      "rateType": "ready"
    },
    {
      "label": "Codegen Success % (All)",
      "type": "line",
      "data": [
        null,
        36.442185514612454,
        40.71870537839124,
        41.35691894312584,
        43.91891891891892,
        43.96339317141852,
        40.61319383900029,
        38.71134020618557
      ],
      "borderColor": "#b45309",
      "backgroundColor": "rgba(255, 255, 255, 0.8)",
      "borderWidth": 3,
      "pointRadius": 3,
      "pointHoverRadius": 5,
      "fill": false,
      "yAxisID": "y1",
      "order": 1,
      "hidden": true,
      "rateType": "total"
    }
  ]
}