{
  "labels": [
    "05/26 14:21",
    "06/02 06:01",
    "06/09 00:01",
    "06/16 03:25",
    "06/23 00:02",
    "07/01 09:02",
    "07/08 18:01",
    "07/16 06:01"
  ],
  "datasets": [
    {
      "label": "Copilot Total",
      "type": "bar",
      "data": [
        8729,
        11274,
        14162,
        16397,
        17819,
        21987,
        29759,
        39572
      ],
      "backgroundColor": "#93c5fd",
      "borderColor": "#93c5fd",
      "borderWidth": 1,
      "yAxisID": "y",
      "order": 2
    },
    {
      "label": "Copilot Merged",
      "type": "bar",
      "data": [
        1594,
        3534,
        5489,
        8364,
        10395,
        12886,
        16959,
        22109
      ],
      "backgroundColor": "#2563eb",
      "borderColor": "#2563eb",
      "borderWidth": 1,
      "yAxisID": "y",
      "order": 2
    },
    {
      "label": "Copilot Success % (Ready)",
      "type": "line",
      "data": [
        75.94092424964268,
        85.05415162454874,
        85.7790279731208,
        91.01196953210011,
        92.10526315789474,
        92.45892229317644,
        92.03842396613481,
        91.6701219006551
      ],
      "borderColor": "#1d4ed8",
      "backgroundColor": "rgba(255, 255, 255, 0.8)",
      "borderWidth": 3,
      "pointRadius": 3,
      "pointHoverRadius": 5,
      "fill": false,
      "yAxisID": "y1",
      "order": 1,
      "rateType": "ready"
    },
    {
      "label": "Copilot Success % (All)",
      "type": "line",
      "data": [
        18.260969183182496,
        31.34646088344864,
        38.75864990820506,
        51.00933097517839,
        58.336606992536055,
        58.60735889389185,
        56.98780200947613,
        55.870312342060046
      ],
      "borderColor": "#1d4ed8",
      "backgroundColor": "rgba(255, 255, 255, 0.8)",
      "borderWidth": 3,
      "pointRadius": 3,
      "pointHoverRadius": 5,
      "fill": false,
      "yAxisID": "y1",
      "order": 1,
      "hidden": true,
      "rateType": "total"
    },
    {
      "label": "Codex Total",
      "type": "bar",
      "data": [
        54211,
        77017,
        207899,
        338382,
        449106,
        558924,
        642761,
        718333
      ],
      "backgroundColor": "#fca5a5",
      "borderColor": "#fca5a5",
      "borderWidth": 1,
      "yAxisID": "y",
      "order": 2
    },
    {
      "label": "Codex Merged",
      "type": "bar",
      "data": [
        44230,
        64142,
        173018,
        286750,
        385095,
        483024,
        557436,
        625131
      ],
      "backgroundColor": "#dc2626",
      "borderColor": "#dc2626",
      "borderWidth": 1,
      "yAxisID": "y",
      "order": 2
    },
    {
      "label": "Codex Success % (Ready)",
      "type": "line",
      "data": [
        85.80352293008458,
        86.4610573423557,
        86.2334840185607,
        87.4240470245336,
        87.79855544307952,
        87.44288434940658,
        87.71171239213761,
        87.96868689569382
      ],
      "borderColor": "#b91c1c",
      "backgroundColor": "rgba(255, 255, 255, 0.8)",
      "borderWidth": 3,
      "pointRadius": 3,
      "pointHoverRadius": 5,
      "fill": false,
      "yAxisID": "y1",
      "order": 1,
      "rateType": "ready"
    },
    {
      "label": "Codex Success % (All)",
      "type": "line",
      "data": [
        81.58860747818709,
        83.28291156497916,
        83.22214152064224,
        84.74150516280416,
        85.74701740791706,
        86.42033621744638,
        86.72523690765308,
        87.02523759871814
      ],
      "borderColor": "#b91c1c",
      "backgroundColor": "rgba(255, 255, 255, 0.8)",
      "borderWidth": 3,
      "pointRadius": 3,
      "pointHoverRadius": 5,
      "fill": false,
      "yAxisID": "y1",
      "order": 1,
      "hidden": true,
      "rateType": "total"
    },
    {
      "label": "Cursor Total",
      "type": "bar",
      "data": [
        null,
        null,
        704,
        1226,
        2022,
        3799,
        11246,
        19012
      ],
      "backgroundColor": "#c4b5fd",
      "borderColor": "#c4b5fd",
      "borderWidth": 1,
      "yAxisID": "y",
      "order": 2
    },
    {
      "label": "Cursor Merged",
      "type": "bar",
      "data": [
        null,
        null,
        543,
        926,
        1497,
        2749,
        8483,
        14363
      ],
      "backgroundColor": "#7c3aed",
      "borderColor": "#7c3aed",
      "borderWidth": 1,
      "yAxisID": "y",
      "order": 2
    },
    {
      "label": "Cursor Success % (Ready)",
      "type": "line",
      "data": [
        null,
        null,
        80.56379821958457,
        78.40812870448772,
        76.41653905053599,
        74.37770562770562,
        76.39589337175792,
        76.25696840987524
      ],
      "borderColor": "#6d28d9",
      "backgroundColor": "rgba(255, 255, 255, 0.8)",
      "borderWidth": 3,
      "pointRadius": 3,
      "pointHoverRadius": 5,
      "fill": false,
      "yAxisID": "y1",
      "order": 1,
      "rateType": "ready"
    },
    {
      "label": "Cursor Success % (All)",
      "type": "line",
      "data": [
        null,
        null,
        77.13068181818183,
        75.53017944535073,
        74.03560830860533,
        72.36114767043958,
        75.43126444958207,
        75.54702293288449
      ],
      "borderColor": "#6d28d9",
      "backgroundColor": "rgba(255, 255, 255, 0.8)",
      "borderWidth": 3,
      "pointRadius": 3,
      "pointHoverRadius": 5,
      "fill": false,
      "yAxisID": "y1",
      "order": 1,
      "hidden": true,
      "rateType": "total"
    },
    {
      "label": "Devin Total",
      "type": "bar",
      "data": [
        null,
        27290,
        27888,
        28750,
        29862,
        29439,
        30435,
        31202
      ],
      "backgroundColor": "#86efac",
      "borderColor": "#86efac",
      "borderWidth": 1,
      "yAxisID": "y",
      "order": 2
    },
    {
      "label": "Devin Merged",
      "type": "bar",
      "data": [
        null,
        16671,
        16967,
        17553,
        18245,
        18789,
        19467,
        19905
      ],
      "backgroundColor": "#059669",
      "borderColor": "#059669",
      "borderWidth": 1,
      "yAxisID": "y",
      "order": 2
    },
    {
      "label": "Devin Success % (Ready)",
      "type": "line",
      "data": [
        null,
        68.0115861618799,
        66.71516200062912,
        66.33786848072563,
        66.0763436187165,
        65.74177746675997,
        65.9361875084677,
        65.81253099685898
      ],
      "borderColor": "#047857",
      "backgroundColor": "rgba(255, 255, 255, 0.8)",
      "borderWidth": 3,
      "pointRadius": 3,
      "pointHoverRadius": 5,
      "fill": false,
      "yAxisID": "y1",
      "order": 1,
      "rateType": "ready"
    },
    {
      "label": "Devin Success % (All)",
      "type": "line",
      "data": [
        null,
        61.08831073653352,
        60.83978772231784,
        61.05391304347826,
        61.0977161610073,
        63.823499439519004,
        63.96254312469196,
        63.79398756489969
      ],
      "borderColor": "#047857",
      "backgroundColor": "rgba(255, 255, 255, 0.8)",
      "borderWidth": 3,
      "pointRadius": 3,
      "pointHoverRadius": 5,
      "fill": false,
      "yAxisID": "y1",
      "order": 1,
      "hidden": true,
      "rateType": "total"
    },
    {
      "label": "Codegen Total",
      "type": "bar",
      "data": [
        null,
        null,
        null,
        4091,
        4090,
        4125,
        4241,
        4462
      ],
      "backgroundColor": "#fed7aa",
      "borderColor": "#fed7aa",
      "borderWidth": 1,
      "yAxisID": "y",
      "order": 2
    },
    {
      "label": "Codegen Merged",
      "type": "bar",
      "data": [
        null,
        null,
        null,
        1523,
        1647,
        1664,
        1728,
        1847
      ],
      "backgroundColor": "#d97706",
      "borderColor": "#d97706",
      "borderWidth": 1,
      "yAxisID": "y",
      "order": 2
    },
    {
      "label": "Codegen Success % (Ready)",
      "type": "line",
      "data": [
        null,
        null,
        null,
        85.46576879910214,
        82.76381909547739,
        80.27013989387362,
        78.94015532206487,
        77.11899791231733
      ],
      "borderColor": "#b45309",
      "backgroundColor": "rgba(255, 255, 255, 0.8)",
      "borderWidth": 3,
      "pointRadius": 3,
      "pointHoverRadius": 5,
      "fill": false,
      "yAxisID": "y1",
      "order": 1,
      "rateType": "ready"
    },
    {
      "label": "Codegen Success % (All)",
      "type": "line",
      "data": [
        null,
        null,
        null,
        37.22806159863114,
        40.26894865525673,
        40.33939393939394,
        40.74510728601745,
        41.393993724787094
      ],
      "borderColor": "#b45309",
      "backgroundColor": "rgba(255, 255, 255, 0.8)",
      "borderWidth": 3,
      "pointRadius": 3,
      "pointHoverRadius": 5,
      "fill": false,
      "yAxisID": "y1",
      "order": 1,
      "hidden": true,
      "rateType": "total"
    }
  ]
}